{"kind":"identitytoolkit#DownloadAccountResponse","users":[{"localId":"3LfQY7qa8tk93HjqkaNyCyxhVXPx","createdAt":"1679056708745","lastLoginAt":"1679135794055","displayName":"Nicky McJay","photoUrl":"","passwordHash":"fakeHash:salt=fakeSaltnNrpaaWUBd7MqEAxLx6E:password=123123","salt":"fakeSaltnNrpaaWUBd7MqEAxLx6E","passwordUpdatedAt":1679186294748,"providerUserInfo":[{"providerId":"password","email":"nicky@jay.com","federatedId":"nicky@jay.com","rawId":"nicky@jay.com","displayName":"Nicky McJay","photoUrl":""}],"validSince":"1679186294","email":"nicky@jay.com","emailVerified":true,"disabled":false},{"localId":"V80MRoOlhzUT3SiUdnetspjyBgJD","createdAt":"1678284011201","lastLoginAt":"1679181641480","displayName":"Peter Hardcore","photoUrl":"","passwordHash":"fakeHash:salt=fakeSaltGbo8jslYfdqN23CBd7E9:password=123123","salt":"fakeSaltGbo8jslYfdqN23CBd7E9","passwordUpdatedAt":1679186294748,"providerUserInfo":[{"providerId":"password","email":"peter@peter.de","federatedId":"peter@peter.de","rawId":"peter@peter.de","displayName":"Peter Hardcore","photoUrl":""}],"validSince":"1679186294","email":"peter@peter.de","emailVerified":true,"disabled":false},{"localId":"jkFoeoGINhJJXXqIra6odQOEVeaG","createdAt":"1678275809665","lastLoginAt":"1679186753951","displayName":"","photoUrl":"","passwordHash":"fakeHash:salt=fakeSalth5tFaOX4lrbBek5QxTm7:password=123123","salt":"fakeSalth5tFaOX4lrbBek5QxTm7","passwordUpdatedAt":1679186294748,"providerUserInfo":[{"providerId":"password","email":"dominik.tajak@gmx.de","federatedId":"dominik.tajak@gmx.de","rawId":"dominik.tajak@gmx.de","displayName":"","photoUrl":""}],"validSince":"1679186294","email":"dominik.tajak@gmx.de","emailVerified":true,"disabled":false,"lastRefreshAt":"2023-03-19T00:45:53.951Z"},{"localId":"x2yc5Kk60Ug2tdFHCkiPd188L7ri","createdAt":"1678268773267","lastLoginAt":"1679184983446","displayName":"Dominik Tajak","photoUrl":"https://lh3.googleusercontent.com/a/AGNmyxY9J_EOP2Hrru3WL7iFHLAw4FG0Kd-G47TdOCO1SA=s96-c","providerUserInfo":[{"providerId":"google.com","rawId":"106568075177293358411","federatedId":"106568075177293358411","displayName":"Dominik Tajak","photoUrl":"https://lh3.googleusercontent.com/a/AGNmyxY9J_EOP2Hrru3WL7iFHLAw4FG0Kd-G47TdOCO1SA=s96-c","email":"domi.tajak@gmail.com"}],"validSince":"1679186294","email":"domi.tajak@gmail.com","emailVerified":true,"disabled":false}]}