{
  "name": "V80MRoOlhzUT3SiUdnetspjyBgJD/events/umohltrZCzWn173EVbJb",
  "bucket": "event-finder-7b8d2.appspot.com",
  "metageneration": 1,
  "generation": 1678370644412,
  "contentType": "image/jpeg",
  "storageClass": "STANDARD",
  "contentDisposition": "inline",
  "downloadTokens": [
    "bf37b7a1-12cb-43c6-9a62-3117a24b95b8"
  ],
  "etag": "4UFg8ZitZiS/mtZ57JuRNBGyOlo",
  "customMetadata": {},
  "timeCreated": "2023-03-09T14:04:04.412Z",
  "updated": "2023-03-09T14:04:04.412Z",
  "size": 86092,
  "md5Hash": "UcpChqk1fJWvTW7/8hQ7IA==",
  "crc32c": "303441787"
}