{
  "name": "x2yc5Kk60Ug2tdFHCkiPd188L7ri/events/QZdITynrTpYuxlcqvX25",
  "bucket": "event-finder-7b8d2.appspot.com",
  "metageneration": 1,
  "generation": 1679060057835,
  "contentType": "image/jpeg",
  "storageClass": "STANDARD",
  "contentDisposition": "inline",
  "downloadTokens": [
    "643ba970-b41c-4ebb-a100-7a88a6a2b522"
  ],
  "etag": "wOlKEejNL8KSD/yzVqD26/rItxg",
  "customMetadata": {},
  "timeCreated": "2023-03-17T13:34:17.836Z",
  "updated": "2023-03-17T13:34:17.836Z",
  "size": 1483806,
  "md5Hash": "4Zta8qdwrur3mSg23Q5tJA==",
  "crc32c": "2219559868"
}